LICENSE
MANIFEST.in
README.md
setup.cfg
setup.py
osm_jet/__init__.py
osm_jet/admin.py
osm_jet/fields.py
osm_jet.egg-info/PKG-INFO
osm_jet.egg-info/SOURCES.txt
osm_jet.egg-info/dependency_links.txt
osm_jet.egg-info/requires.txt
osm_jet.egg-info/top_level.txt
osm_jet/dashboard/__init__.py
osm_jet/dashboard/dashboard.py
osm_jet/dashboard/modules.py
osm_jet/static/.DS_Store
osm_jet/static/admin/auth/login.css
osm_jet/static/admin/edit_inline/compact_inline.css
osm_jet/static/admin/edit_inline/stacked_inline.css
osm_jet/static/admin/edit_inline/stacked_inline.js
osm_jet/static/admin/edit_inline/tabular_inline.css
osm_jet/static/admin/edit_inline/tabular_inline.js
osm_jet/static/admin/sortable/sortables.min.js
osm_jet/static/admin/widgets/many2many.css
osm_jet/static/admin/widgets/many2many.js
osm_jet/static/img/login-background.jpg
osm_jet/static/jet/css/_base.scss
osm_jet/static/jet/css/_breadcrumbs.scss
osm_jet/static/jet/css/_changeform.scss
osm_jet/static/jet/css/_changelist.scss
osm_jet/static/jet/css/_content.scss
osm_jet/static/jet/css/_dashboard.scss
osm_jet/static/jet/css/_delete-confirmation.scss
osm_jet/static/jet/css/_fonts.scss
osm_jet/static/jet/css/_forms.scss
osm_jet/static/jet/css/_globals.scss
osm_jet/static/jet/css/_header.scss
osm_jet/static/jet/css/_helpers.scss
osm_jet/static/jet/css/_image-editor.scss
osm_jet/static/jet/css/_login.scss
osm_jet/static/jet/css/_messages.scss
osm_jet/static/jet/css/_modules.scss
osm_jet/static/jet/css/_object-tools.scss
osm_jet/static/jet/css/_relatedpopup.scss
osm_jet/static/jet/css/_sidebar.scss
osm_jet/static/jet/css/_tables.scss
osm_jet/static/jet/css/_variables.scss
osm_jet/static/jet/css/vendor.css
osm_jet/static/jet/css/icons/_variables.scss
osm_jet/static/jet/css/icons/down-arrow.svg
osm_jet/static/jet/css/icons/style.css
osm_jet/static/jet/css/icons/fonts/jet-icons.eot
osm_jet/static/jet/css/icons/fonts/jet-icons.svg
osm_jet/static/jet/css/icons/fonts/jet-icons.ttf
osm_jet/static/jet/css/icons/fonts/jet-icons.woff
osm_jet/static/jet/css/jquery-ui/_jquery-ui.theme.scss
osm_jet/static/jet/css/jquery-ui/images/ui-bg_flat_0_aaaaaa_40x100.png
