Metadata-Version: 1.1
Name: osm-jet
Version: 1.1.12
Summary: A CMS skin for Django. An extension of django-jet with some fixes and additional features
Home-page: https://github.com/onespacemedia/osm_jet
Author: Onespacemedia
Author-email: developers@onespacemedia.com
License: agpl-3.0
Platform: UNKNOWN
Classifier: Development Status :: 3 - Alpha
Classifier: Intended Audience :: Developers
Classifier: Framework :: Django :: 1.11
Classifier: License :: OSI Approved :: GNU Affero General Public License v3
Classifier: Natural Language :: English
Classifier: Programming Language :: Python :: 3
Classifier: Programming Language :: Python :: 3.5
Classifier: Programming Language :: Python :: 3.6
